{
  "updatedAt": "2026-04-09",
  "source": "Legacy egg guide dataset normalized from articles/adopt-me-egg-guide.html",
  "eggs": [
  {"id":"cracked","name":"Cracked Egg","cost":"350 Bucks","type":"bucks","status":"available","released":"Jun 2019","img":"e/ec/AM_Cracked_Egg.png","chances":{"Common":"45%","Uncommon":"33%","Rare":"14.5%","Ultra-Rare":"6%","Legendary":"1.5%"},"pets":[["Ant","5/56/Ant.png","Common"],["Mouse","5/5c/Mouse.png","Common"],["Buffalo","0/0a/Buffalo.png","Common"],["Cat","7/7e/Cat_Icon.png","Common"],["Dog","3/35/Dog.png","Common"],["Chicken","7/78/Chicken.png","Common"],["Camel","0/09/Camel.png","Uncommon"],["Donkey","9/95/Donkey.png","Uncommon"],["Poodle","7/7d/Poodle.png","Uncommon"],["Puma","6/63/Puma.png","Uncommon"],["Snow Cat","3/3e/Snow_Cat2.png","Uncommon"],["Chocolate Labrador","1/17/Chocolate_Labrador2.png","Uncommon"],["Fennec Fox","b/bc/Fennec_Fox_AM.png","Uncommon"],["Orangutan","d/dd/Orangutan.png","Rare"],["Parakeet","7/7c/Parakeet.png","Rare"],["Zebra","3/37/Zebra.png","Rare"],["Blue Dog","8/8d/Blue_Dog.png","Rare"],["Lamb","e/e8/Lamb.png","Rare"],["Pig","c/c7/Pig.png","Rare"],["Dalmatian","6/6d/Dalmatian.png","Ultra-Rare"],["Horse","c/c6/Horse.png","Ultra-Rare"],["Corgi","1/12/Corgi.png","Ultra-Rare"],["Dragon","3/3c/Dragon_Pet.png","Legendary"],["Unicorn","1/1f/Unicorn_Pet.png","Legendary"]]},
  {"id":"pet","name":"Pet Egg","cost":"600 Bucks","type":"bucks","status":"available","released":"Jun 2019","img":"2/2b/Pet_Egg.png","chances":{"Common":"20%","Uncommon":"35%","Rare":"27%","Ultra-Rare":"15%","Legendary":"3%"},"pets":[["Dog","3/35/Dog.png","Common"],["Cat","7/7e/Cat_Icon.png","Common"],["Otter","a/a3/Otter_AM.png","Common"],["Chocolate Labrador","1/17/Chocolate_Labrador2.png","Uncommon"],["Fennec Fox","b/bc/Fennec_Fox_AM.png","Uncommon"],["Puma","6/63/Puma.png","Uncommon"],["Snow Cat","3/3e/Snow_Cat2.png","Uncommon"],["Rabbit","9/94/Rabbit1.png","Uncommon"],["Drake","4/46/Drake.png","Uncommon"],["Turkey","5/5b/Turkey.png","Uncommon"],["Beaver","2/26/Beaver.png","Rare"],["Bunny","a/a9/Bunny2.png","Rare"],["Blue Dog","8/8d/Blue_Dog.png","Rare"],["Lamb","e/e8/Lamb.png","Rare"],["Pig","c/c7/Pig.png","Rare"],["Dalmatian","6/6d/Dalmatian.png","Ultra-Rare"],["Horse","c/c6/Horse.png","Ultra-Rare"],["Griffin","e/e7/Griffin.png","Ultra-Rare"],["Dragon","3/3c/Dragon_Pet.png","Legendary"],["Unicorn","1/1f/Unicorn_Pet.png","Legendary"]]},
  {"id":"royal","name":"Royal Egg","cost":"1,450 Bucks","type":"bucks","status":"available","released":"Jun 2019","img":"3/32/AM_Royal_Egg.png","chances":{"Common":"0%","Uncommon":"25%","Rare":"37%","Ultra-Rare":"30%","Legendary":"8%"},"pets":[["Bunny","a/a9/Bunny2.png","Uncommon"],["Rabbit","9/94/Rabbit1.png","Uncommon"],["Drake","4/46/Drake.png","Uncommon"],["Turkey","5/5b/Turkey.png","Uncommon"],["Otter","a/a3/Otter_AM.png","Uncommon"],["Beaver","2/26/Beaver.png","Rare"],["Lamb","e/e8/Lamb.png","Rare"],["Pig","c/c7/Pig.png","Rare"],["Blue Dog","8/8d/Blue_Dog.png","Rare"],["Dalmatian","6/6d/Dalmatian.png","Ultra-Rare"],["Horse","c/c6/Horse.png","Ultra-Rare"],["Griffin","e/e7/Griffin.png","Ultra-Rare"],["Crow","4/4d/Crow.png","Ultra-Rare"],["Dragon","3/3c/Dragon_Pet.png","Legendary"],["Unicorn","1/1f/Unicorn_Pet.png","Legendary"]]},
  {"id":"retired","name":"Retired Egg","cost":"600 Bucks (VIP)","type":"bucks","status":"available","released":"Jul 2022","img":"b/b5/Retired_Egg_inventory.png","chances":{"Common":"20%","Uncommon":"35%","Rare":"27%","Ultra-Rare":"15%","Legendary":"3%"},"pets":[["Buffalo","0/0a/Buffalo.png","Common"],["Cat","7/7e/Cat_Icon.png","Common"],["Dog","3/35/Dog.png","Common"],["Otter","a/a3/Otter_AM.png","Common"],["Chocolate Labrador","1/17/Chocolate_Labrador2.png","Uncommon"],["Fennec Fox","b/bc/Fennec_Fox_AM.png","Uncommon"],["Puma","6/63/Puma.png","Uncommon"],["Snow Cat","3/3e/Snow_Cat2.png","Uncommon"],["Beaver","2/26/Beaver.png","Rare"],["Bunny","a/a9/Bunny2.png","Rare"],["Rabbit","9/94/Rabbit1.png","Rare"],["Snow Puma","d/de/SnowPuma.png","Rare"],["Red Panda","8/8b/Red_Panda.png","Ultra-Rare"],["Shiba Inu","0/03/ShibaInu_Pet.png","Ultra-Rare"],["Dragon","3/3c/Dragon_Pet.png","Legendary"],["Unicorn","1/1f/Unicorn_Pet.png","Legendary"]]},
  {"id":"safari","name":"Safari Egg","cost":"750 Robux","type":"robux","status":"retired","released":"Aug 2019","retired":"Sep 2019","img":"9/9a/Safari_Egg.png","chances":{"Common":"0%","Uncommon":"45%","Rare":"37%","Ultra-Rare":"15%","Legendary":"3%"},"pets":[["Brown Bear","5/58/Brown_Bear.png","Uncommon"],["Puma","6/63/Puma.png","Uncommon"],["Flamingo","e/ec/Flamingo.png","Rare"],["Hyena","8/8e/Hyena.png","Rare"],["Rhino","c/c2/Rhino.png","Rare"],["Lion","a/a9/Lion.png","Ultra-Rare"],["Giraffe","b/b7/Giraffe.png","Legendary"]]},
  {"id":"jungle","name":"Jungle Egg","cost":"750 Robux","type":"robux","status":"retired","released":"Sep 2019","retired":"Nov 2019","img":"c/c9/Jungle_Egg.png","chances":{"Common":"0%","Uncommon":"45%","Rare":"37%","Ultra-Rare":"15%","Legendary":"3%"},"pets":[["Black Panther","f/f2/Black_Panther.png","Uncommon"],["Capybara","6/6e/Capybara.png","Uncommon"],["Brown Bear","5/58/Brown_Bear.png","Rare"],["Rhino","c/c2/Rhino.png","Rare"],["Crocodile","d/d6/Crocodile.png","Ultra-Rare"],["Platypus","5/5d/Platypus.png","Ultra-Rare"],["Parrot","3/38/Parrot.png","Legendary"]]},
  {"id":"farm","name":"Farm Egg","cost":"750 Robux","type":"robux","status":"retired","released":"Nov 2019","retired":"Feb 2020","img":"0/06/FarmEgg.png","chances":{"Common":"20%","Uncommon":"35%","Rare":"27%","Ultra-Rare":"15%","Legendary":"3%"},"pets":[["Chicken","7/78/Chicken.png","Common"],["Pig","c/c7/Pig.png","Common"],["Turkey","5/5b/Turkey.png","Uncommon"],["Robin","5/55/Robin.png","Uncommon"],["Bunny","a/a9/Bunny2.png","Uncommon"],["Cow","e/ee/Cow.png","Rare"],["Lamb","e/e8/Lamb.png","Rare"],["Rabbit","9/94/Rabbit1.png","Ultra-Rare"],["Horse","c/c6/Horse.png","Ultra-Rare"]]},
  {"id":"aussie","name":"Aussie Egg","cost":"750 Robux","type":"robux","status":"retired","released":"Feb 2020","retired":"Oct 2020","img":"1/16/Aussie_Egg.png","chances":{"Common":"30%","Uncommon":"25%","Rare":"27%","Ultra-Rare":"15%","Legendary":"3%"},"pets":[["Bandicoot","b/bf/Bandicoot.png","Common"],["Dingo","d/d5/Dingo.png","Uncommon"],["Crocodile","d/d6/Crocodile.png","Uncommon"],["Emu","e/ee/Emu.png","Rare"],["Koala","3/3f/Koala_Pet.png","Rare"],["Platypus","5/5d/Platypus.png","Ultra-Rare"],["Tasmanian Tiger","4/4a/Tasmanian_Tiger.png","Ultra-Rare"],["Kangaroo","8/8c/Kangaroo.png","Legendary"]]},
  {"id":"fossil","name":"Fossil Egg","cost":"750 Robux","type":"robux","status":"retired","released":"Oct 2020","retired":"Apr 2021","img":"1/14/Fossil_Egg.png","chances":{"Common":"25%","Uncommon":"30%","Rare":"25%","Ultra-Rare":"15%","Legendary":"5%"},"pets":[["Ground Sloth","5/52/Ground_Sloth.png","Common"],["Dilophosaurus","d/d4/Dilophosaurus.png","Common"],["Triceratops","e/ef/Triceratops.png","Uncommon"],["Pterodactyl","a/ae/Pterodactyl.png","Uncommon"],["Tasmanian Tiger","4/4a/Tasmanian_Tiger.png","Uncommon"],["Wooly Mammoth","7/77/Wooly_Mammoth.png","Rare"],["Stegosaurus","0/09/Stegosaurus.png","Rare"],["Sabertooth","a/a4/Sabertooth.png","Rare"],["Glyptodon","d/d1/Glyptodon.png","Ultra-Rare"],["Dodo","a/a4/Dodo.png","Ultra-Rare"],["Diplodocus","d/d9/Diplodocus.png","Legendary"],["T-Rex","1/1d/T-Rex.png","Legendary"]]},
  {"id":"ocean","name":"Ocean Egg","cost":"750 Robux","type":"robux","status":"retired","released":"Apr 2021","retired":"Aug 2021","img":"a/a5/Images-Ocean-Egg.png","chances":{"Common":"20%","Uncommon":"35%","Rare":"30%","Ultra-Rare":"10%","Legendary":"5%"},"pets":[["Seahorse","a/a1/Seahorse.png","Common"],["Octopus","b/b7/Images-Octopus.png","Uncommon"],["Clownfish","2/29/Clownfish.png","Uncommon"],["Sea Turtle","f/f0/Sea_Turtle.png","Rare"],["Narwhal","b/b7/Narwhal.png","Rare"],["Frog","8/84/Frog.png","Rare"],["Shark","1/1e/Shark.png","Ultra-Rare"],["Dolphin","7/72/Dolphin.png","Legendary"]]},
  {"id":"mythic","name":"Mythic Egg","cost":"750 Robux","type":"robux","status":"retired","released":"Aug 2021","retired":"Mar 2022","img":"9/92/Mythic_Egg.png","chances":{"Common":"22%","Uncommon":"19%","Rare":"34%","Ultra-Rare":"20%","Legendary":"5%"},"pets":[["Wolpertinger","2/20/Wolpertinger.png","Common"],["Kirin","8/84/KirinIcon.png","Uncommon"],["Merhorse","f/f3/MerhorseIcon.png","Rare"],["Sasquatch","6/65/SasquatchIcon.png","Rare"],["Hydra","0/03/HydraIcon.png","Ultra-Rare"],["Wyvern","7/77/WyvernIcon.png","Ultra-Rare"],["Goldhorn","0/0b/GoldenHornMain-Render.png","Legendary"],["Phoenix","2/2a/PhoenixIcon.png","Legendary"]]},
  {"id":"japan","name":"Japan Egg","cost":"750 Robux","type":"robux","status":"retired","released":"Mar 2022","retired":"Jun 2022","img":"2/25/Japan_Egg.png","chances":{"Common":"22%","Uncommon":"19%","Rare":"34%","Ultra-Rare":"20%","Legendary":"5%"},"pets":[["Shiba Inu","0/03/ShibaInu_Pet.png","Common"],["Red Fox","e/e3/Red_Fox.png","Common"],["Deer","8/81/Deer.png","Uncommon"],["Snow Leopard","3/38/Snow_Leopard.png","Uncommon"],["Red Panda","8/8b/Red_Panda.png","Rare"],["Crane","6/6b/Crane.png","Rare"],["Tanuki","e/e1/Tanuki.png","Rare"],["Snow Monkey","7/70/Snow_Monkey.png","Rare"],["Giant Panda","6/65/Giant_Panda.png","Ultra-Rare"],["Koi Fish","3/30/Koi_Fish.png","Ultra-Rare"],["Kitsune","f/f6/Kitsune.png","Legendary"],["White Tiger","6/63/White_Tiger.png","Legendary"]]},
  {"id":"woodland","name":"Woodland Egg","cost":"750 Robux","type":"robux","status":"retired","released":"Sep 2023","retired":"Jan 2024","img":"2/22/Woodland_Egg.png","chances":{"Common":"22%","Uncommon":"19%","Rare":"34%","Ultra-Rare":"20%","Legendary":"5%"},"pets":[["Deer","8/81/Deer.png","Common"],["Hedgehog","0/09/Hedgehog.png","Uncommon"],["Fox","6/6b/Fox.png","Rare"],["Owl","4/46/Owl.png","Rare"],["Raccoon","5/5b/Raccoon.png","Rare"],["Bat","d/d0/Bat.png","Ultra-Rare"],["Wolf","b/bf/Wolf.png","Ultra-Rare"],["Red Dragon","f/f5/Red_Dragon.png","Legendary"]]},
  {"id":"desert","name":"Desert Egg","cost":"750 Robux","type":"robux","status":"retired","released":"Jan 2024","retired":"May 2024","img":"8/8d/Desert_Egg.png","chances":{"Common":"40%","Uncommon":"25%","Rare":"17%","Ultra-Rare":"14%","Legendary":"4%"},"pets":[["Armadillo","9/9f/Armadillo.png","Common"],["Coyote","0/02/Coyote.png","Common"],["Sandfish","b/bb/Sandfish.png","Common"],["Gila Monster","5/59/Gila_Monster.png","Uncommon"],["Rattlesnake","6/6c/Rattlesnake.png","Uncommon"],["Oryx","6/64/Oryx.png","Uncommon"],["Thorny Devil","f/fc/Thorny_Devil.png","Rare"],["Deathstalker Scorpion","1/1f/Deathstalker_Scorpion.png","Rare"],["Roadrunner","0/05/Roadrunner.png","Ultra-Rare"],["Vulture","0/01/Vulture.png","Ultra-Rare"],["Cactus Friend","e/e8/Cactus_Friend_%28Pet%29.png","Legendary"],["Criosphinx","0/01/Criosphinx.png","Legendary"]]},
  {"id":"garden","name":"Garden Egg","cost":"750 Robux","type":"robux","status":"retired","released":"May 2024","retired":"Jan 2025","img":"3/3d/Garden_Egg.png","chances":{"Common":"35%","Uncommon":"25%","Rare":"24%","Ultra-Rare":"12%","Legendary":"4%"},"pets":[["Garden Snake","8/80/Garden_Snake.png","Common"],["Mole","6/63/Mole.png","Uncommon"],["Weevil","8/81/Weevil.png","Rare"],["Blue Jay","8/87/Blue_Jay.png","Rare"],["Praying Mantis","c/c7/Praying_Mantis.png","Ultra-Rare"],["Skunk","7/79/Skunk.png","Ultra-Rare"],["Rosy Maple Moth","5/59/Rosy_Maple_Moth.png","Legendary"],["Mushroom Friend","e/ed/Mushroom_Friend.png","Legendary"]]},
  {"id":"moon","name":"Moon Egg","cost":"750 Robux","type":"robux","status":"retired","released":"Feb 2025","retired":"Aug 2025","img":"0/01/Moon_Egg.png","chances":{"Common":"35%","Uncommon":"25%","Rare":"24%","Ultra-Rare":"12%","Legendary":"4%"},"pets":[["Hopbop","c/c5/HopBop.png","Common"],["Snorgle","5/5b/Snorgle.png","Uncommon"],["Moonpine","4/4e/Moonpine.png","Rare"],["Zeopod","7/7c/Zeopod.png","Rare"],["Puptune","2/29/Puptune.png","Ultra-Rare"],["Starmite","1/1b/Starmite.png","Ultra-Rare"],["Dimension Drifter","a/a9/Dimension_Drifter.png","Ultra-Rare"],["Sunglider","e/ea/Sunglider.png","Legendary"]]},
  {"id":"aztec","name":"Aztec Egg","cost":"750 Robux","type":"robux","status":"retired","released":"Aug 2025","retired":"Feb 2026","img":"c/cc/Aztec_Egg.png","chances":{"Common":"35%","Uncommon":"25%","Rare":"24%","Ultra-Rare":"12%","Legendary":"4%"},"pets":[["Tegu","6/69/Tegu.png","Common"],["Tree Frog","1/13/Tree_Frog.png","Uncommon"],["Chanekeh","a/a3/Chanekeh.png","Rare"],["Water Opossum","b/b3/Water_Opossum.png","Rare"],["Ehecatl","2/20/Ehecatl.png","Ultra-Rare"],["Onza","c/ce/Onza.png","Ultra-Rare"],["Quetzalcoatl","6/61/Quetzalcoatl.png","Legendary"],["Temple Friend","e/e2/Temple_Friend.png","Legendary"]]},
  {"id":"endangered","name":"Endangered Egg","cost":"750 Robux","type":"robux","status":"available","released":"Feb 2026","img":"c/ce/Endangered_Egg.png","chances":{"Common":"35%","Uncommon":"30%","Rare":"20%","Ultra-Rare":"12%","Legendary":"3%"},"pets":[["California Condor","6/6a/California_Condor.png","Common"],["Galapagos Sea Lion","7/74/Galapagos_Sea_Lion.png","Common"],["Black Tiger","0/0e/Black_Tiger.png","Uncommon"],["Kakapo","4/45/Kakapo.png","Uncommon"],["Black Rhino","0/0f/Black_Rhino.png","Rare"],["Mexican Wolf","6/63/Mexican_Wolf.png","Rare"],["Black-Footed Ferret","0/07/Black-Footed_Ferret.png","Rare"],["Pangolin","2/28/Pangolin.png","Ultra-Rare"],["Blue Whale","d/dc/Blue_Whale.png","Legendary"],["Sea Turtle","f/f0/Sea_Turtle.png","Legendary"]]},
  {"id":"basic","name":"Basic Egg","cost":"400 Tickets","type":"tickets","status":"available","released":"Sep 2025","img":"f/fa/Basic_Egg.png","chances":{"Common":"59.75%","Uncommon":"35%","Rare":"4%","Ultra-Rare":"0.99%","Legendary":"0.26%"},"pets":[["Ant","5/56/Ant.png","Common"],["California Condor","6/6a/California_Condor.png","Common"],["Galapagos Sea Lion","7/74/Galapagos_Sea_Lion.png","Common"],["Mouse","5/5c/Mouse.png","Common"],["Black Tiger","0/0e/Black_Tiger.png","Uncommon"],["Camel","0/09/Camel.png","Uncommon"],["Donkey","9/95/Donkey.png","Uncommon"],["Kakapo","4/45/Kakapo.png","Uncommon"],["Poodle","7/7d/Poodle.png","Uncommon"],["Black Rhino","0/0f/Black_Rhino.png","Rare"],["Mexican Wolf","6/63/Mexican_Wolf.png","Rare"],["Orangutan","d/dd/Orangutan.png","Rare"],["Parakeet","7/7c/Parakeet.png","Rare"],["Zebra","3/37/Zebra.png","Rare"],["Black-Footed Ferret","0/07/Black-Footed_Ferret.png","Ultra-Rare"],["Corgi","1/12/Corgi.png","Ultra-Rare"],["Pangolin","2/28/Pangolin.png","Ultra-Rare"],["Pomeranian","c/c1/Pomeranian.png","Ultra-Rare"],["Swordfish","f/f7/Swordfish.png","Ultra-Rare"],["Alicorn","1/17/Alicorn.png","Legendary"],["Ancient Dragon","7/77/Ancient_Dragon.png","Legendary"],["Blue Whale","d/dc/Blue_Whale.png","Legendary"],["Dragonfly","8/84/Dragonfly.png","Legendary"],["Sea Turtle","f/f0/Sea_Turtle.png","Legendary"],["Silverback Gorilla","2/22/Silverback_Gorilla.png","Legendary"]]},
  {"id":"crystal","name":"Crystal Egg","cost":"4,000 Tickets","type":"tickets","status":"available","released":"Sep 2025","img":"6/6d/Crystal_Egg.png","chances":{"Common":"0%","Uncommon":"0%","Rare":"50%","Ultra-Rare":"44%","Legendary":"6%"},"pets":[["Abyssinian Cat","1/14/Abyssinian_Cat.png","Rare"],["Black Rhino","0/0f/Black_Rhino.png","Rare"],["Mexican Wolf","6/63/Mexican_Wolf.png","Rare"],["Ocelot","0/0d/Ocelot.png","Rare"],["Orangutan","d/dd/Orangutan.png","Rare"],["Parakeet","7/7c/Parakeet.png","Rare"],["Zebra","3/37/Zebra.png","Rare"],["Badger","f/ff/Badger.png","Rare"],["Black-Footed Ferret","0/07/Black-Footed_Ferret.png","Ultra-Rare"],["Corgi","1/12/Corgi.png","Ultra-Rare"],["Ginger Cat","0/09/Ginger_Cat_%28transparent%29.png","Ultra-Rare"],["Grinmoire","5/5a/Grinmoire.png","Ultra-Rare"],["Orca","7/75/Orca.png","Ultra-Rare"],["Pangolin","2/28/Pangolin.png","Ultra-Rare"],["Pomeranian","c/c1/Pomeranian.png","Ultra-Rare"],["Ribbon Seal","c/c9/Ribbon_Seal.png","Ultra-Rare"],["Starfish","5/52/Starfish.png","Ultra-Rare"],["Swordfish","f/f7/Swordfish.png","Ultra-Rare"],["Toucan","7/7a/AM_Toucan.png","Ultra-Rare"],["Waffle Wyrm","4/40/Waffle_Wyrm.png","Ultra-Rare"],["Alicorn","1/17/Alicorn.png","Legendary"],["Ancient Dragon","7/77/Ancient_Dragon.png","Legendary"],["Blue Whale","d/dc/Blue_Whale.png","Legendary"],["Diamond Dragon","9/9b/DiamondDragon_Pet.png","Legendary"],["Diamond Griffin","7/7a/DiamondGrififn_Pet.png","Legendary"],["Diamond Unicorn","6/6b/DiamondUnicorn_Pet.png","Legendary"],["Dragonfruit Fox","e/e6/Dragon_Fruit_Fox.png","Legendary"],["Dragonfly","8/84/Dragonfly.png","Legendary"],["Emberlight","c/c1/Emberlight.png","Legendary"],["Golden Dragon","a/a6/GoldenDragon_Pet.png","Legendary"],["Golden Griffin","3/35/GoldenGriffin_Pet.png","Legendary"],["Golden Unicorn","9/99/GoldenUnicorn_Pet.png","Legendary"],["Sea Turtle","f/f0/Sea_Turtle.png","Legendary"],["Silverback Gorilla","2/22/Silverback_Gorilla.png","Legendary"]]}
]
}
